setup.py
baizhanSuperMath/__init__.py
baizhanSuperMath/demo1.py
baizhanSuperMath/demo2.py
baizhankkkSuperMath.egg-info/PKG-INFO
baizhankkkSuperMath.egg-info/SOURCES.txt
baizhankkkSuperMath.egg-info/dependency_links.txt
baizhankkkSuperMath.egg-info/top_level.txt