Metadata-Version: 2.1
Name: baizhankkkSuperMath
Version: 2.5
Summary: 这是第一个对外发布的模块，里面只有数学方法，用于测试哦
Author: gaoqi
Author-email: gaoqi110@163.com
